{"date": "2026-05-01", "generated": "2026-04-30T05:32:59", "total_releases": 97, "catalog_releases": 4, "new_albums": 4, "reissues": 0, "by_genre": {"METAL": [{"artist": "Behemoth", "album": "The Apostasy", "release_type": "new", "subgenre": "EXTREME", "tracks": [{"title": "Rome 64 C.E.", "track_number": 1, "duration_ms": 76560}, {"title": "Slaying the Prophets ov Isa", "track_number": 2, "duration_ms": 203146}, {"title": "Prometherion", "track_number": 3, "duration_ms": 183426}, {"title": "At the Left Hand ov God", "track_number": 4, "duration_ms": 298346}, {"title": "Kriegsphilosophie", "track_number": 5, "duration_ms": 263600}, {"title": "Be Without Fear", "track_number": 6, "duration_ms": 197320}, {"title": "Arcana Hereticae", "track_number": 7, "duration_ms": 178173}, {"title": "Libertheme", "track_number": 8, "duration_ms": 293240}, {"title": "Inner Sanctum", "track_number": 9, "duration_ms": 301480}, {"title": "Pazuzu", "track_number": 10, "duration_ms": 157026}, {"title": "Christgrinding Avenue", "track_number": 11, "duration_ms": 223000}], "total_tracks": 11, "runtime_ms": 2375317}, {"artist": "Sevendust", "album": "ONE", "release_type": "new", "subgenre": "NU METAL / ALT METAL", "cover_art": {"small": "https://coverartarchive.org/release/3f00744b-2820-4286-a138-71bc31ea5451/44217048183-250.jpg", "large": "https://coverartarchive.org/release/3f00744b-2820-4286-a138-71bc31ea5451/44217048183-500.jpg"}, "tracks": [{"title": "One", "track_number": 1, "duration_ms": 228365}, {"title": "Unbreakable", "track_number": 2, "duration_ms": 251480}, {"title": "Is This the Real You", "track_number": 3, "duration_ms": 226728}, {"title": "Threshold", "track_number": 4, "duration_ms": 220282}, {"title": "We Won", "track_number": 5, "duration_ms": 231770}, {"title": "Construct", "track_number": 6, "duration_ms": 237207}, {"title": "Bright Side", "track_number": 7, "duration_ms": 215820}, {"title": "The Drop", "track_number": 8, "duration_ms": 230483}, {"title": "Blood Price", "track_number": 9, "duration_ms": 241322}, {"title": "Misdirection", "track_number": 10, "duration_ms": 313964}], "total_tracks": 10, "runtime_ms": 2397421}], "ROCK": [{"artist": "Tori Amos", "album": "In Times of Dragons", "release_type": "new", "subgenre": "CLASSIC / ARENA ROCK", "tracks": [{"title": "Shush", "track_number": 1, "duration_ms": 375000}, {"title": "In Times of Dragons", "track_number": 2, "duration_ms": 290000}, {"title": "Provincetown", "track_number": 3, "duration_ms": 305000}, {"title": "St. Theresa", "track_number": 4, "duration_ms": 379000}, {"title": "Gasoline Girls", "track_number": 5, "duration_ms": 176000}, {"title": "Ode to Minnesota", "track_number": 6, "duration_ms": 94000}, {"title": "Fanny Faudrey", "track_number": 7, "duration_ms": 107000}, {"title": "Veins", "track_number": 8, "duration_ms": 239000}, {"title": "Strawberry Moon", "track_number": 9, "duration_ms": 250000}, {"title": "Song of Sorrow", "track_number": 10, "duration_ms": 379000}, {"title": "Flood", "track_number": 11, "duration_ms": 243000}, {"title": "Pyrite", "track_number": 12, "duration_ms": 214000}, {"title": "Tempest", "track_number": 13, "duration_ms": 318000}, {"title": "Angelshark", "track_number": 14, "duration_ms": 227000}, {"title": "Blue Lotus", "track_number": 15, "duration_ms": 363000}, {"title": "Stronger Together", "track_number": 16, "duration_ms": 194000}, {"title": "23 Peaks", "track_number": 17, "duration_ms": 402000}], "total_tracks": 17, "runtime_ms": 4555000}], "SOUL / R&B": [{"artist": "Taj Mahal / Phantom Blues Band", "album": "Time", "release_type": "new", "subgenre": "MODERN R&B", "cover_art": {"small": "https://coverartarchive.org/release/7fd2fb4e-d368-4d5d-954d-c00d1c5b89b0/44737890184-250.jpg", "large": "https://coverartarchive.org/release/7fd2fb4e-d368-4d5d-954d-c00d1c5b89b0/44737890184-500.jpg"}, "tracks": [{"title": "Life of Love", "track_number": 1, "duration_ms": 216000}, {"title": "Wild About My Lovin'", "track_number": 2, "duration_ms": 343000}, {"title": "Crazy About A Jukebox", "track_number": 3, "duration_ms": 240000}, {"title": "Time", "track_number": 4, "duration_ms": 221000}, {"title": "You Put The Whammy On Me", "track_number": 5, "duration_ms": 198000}, {"title": "Talkin' Blues", "track_number": 6, "duration_ms": 276000}, {"title": "Sweet Lorene", "track_number": 7, "duration_ms": 179000}, {"title": "Ask Me About Nothing (But The Blues)", "track_number": 8, "duration_ms": 248000}, {"title": "It's Your Voodoo Working", "track_number": 9, "duration_ms": 195000}, {"title": "Rowdy Blues", "track_number": 10, "duration_ms": 260000}], "total_tracks": 10, "runtime_ms": 2376000}]}, "candidates": [{"artist": "Zara Larsson", "artist_mbid": "134e6410-6954-45d1-bd4a-0f2d2ad5471d", "album": "Midnight Sun: Girls Trip", "release_mbid": "dce5bc25-bff7-460c-9a0f-1d7261763048", "release_type": "new", "wikidata_qid": "Q4177928", "sitelinks": 65}, {"artist": "Melanie C", "artist_mbid": "25b509ef-48ad-461b-a0bc-94cdddb8c919", "album": "Sweat", "release_mbid": "da8672df-a334-498f-8dba-380df45e93db", "release_type": "new", "wikidata_qid": "Q151830", "sitelinks": 53}, {"artist": "Maya Hawke", "artist_mbid": "6879c573-d161-427c-8b67-77d65fa477bb", "album": "Maitreya Corso", "release_mbid": "d75edc2b-9be9-4197-add7-22d1bd4e44c9", "release_type": "new", "wikidata_qid": "Q46994907", "sitelinks": 48}, {"artist": "Laibach", "artist_mbid": "c779e090-909f-4403-a90e-c1d08cdbb719", "album": "MUSICK", "release_mbid": "a84e3e01-b90a-4bf0-ad7c-c317d91dfb0a", "release_type": "new", "wikidata_qid": "Q325359", "sitelinks": 44}, {"artist": "Kacey Musgraves", "artist_mbid": "d1393ecb-431b-4fde-a6ea-d769f2f040cb", "album": "Middle of Nowhere", "release_mbid": "6f82f19f-6e32-4e5c-94b5-bd14693d1317", "release_type": "new", "wikidata_qid": "Q2783855", "sitelinks": 39}, {"artist": "UFO", "artist_mbid": "c0bf9e20-2872-4897-ad1f-0882b83272a0", "album": "The Wild, the Willing and the Innocent", "release_mbid": "fbd1f5a4-b46d-46a5-b086-d56cc695035b", "release_type": "new", "wikidata_qid": "Q251657", "sitelinks": 32}, {"artist": "KNEECAP", "artist_mbid": "6ac275dd-eb37-42cf-9a60-6b147320c7be", "album": "FENIAN", "release_mbid": "1ab785c7-afaf-4a16-a367-f15358048c23", "release_type": "new", "wikidata_qid": "Q65327538", "sitelinks": 30}, {"artist": "Lil Tjay", "artist_mbid": "d44b92db-dd49-4636-abe8-7c381f90b7aa", "album": "They Just Ain't You", "release_mbid": "953df651-46d3-4a86-92b5-bf533627d533", "release_type": "new", "wikidata_qid": "Q61670761", "sitelinks": 22}]}